usfmtc/__init__.py
usfmtc/eng.vrs
usfmtc/extension.py
usfmtc/lxmlutils.py
usfmtc/org.vrs
usfmtc/reference.py
usfmtc/usfmgenerate.py
usfmtc/usfmparser.py
usfmtc/usjproc.py
usfmtc/usx.rng
usfmtc/usxcursor.py
usfmtc/usxmodel.py
usfmtc/utils.py
usfmtc/versification.py
usfmtc/xmlutils.py
usfmtc/diagrams/diagrams.py
usfmtc/diagrams/railroad.py
usfmtc/diagrams/usxgrammar.py
usfmtc/rnc2rng/__init__.py
usfmtc/rnc2rng/parser.py
usfmtc/rnc2rng/rnctree.py
usfmtc/rnc2rng/serializer.py
usfmtc/validating/rngparser.py
usfmtc/validating/usfmgrammar.py
usfmtc/validating/usfmparser.py
usfmtc/validating/usxparser.py
usfmtc-0.4.3.dist-info/licenses/LICENSE
usfmtc-0.4.3.dist-info/METADATA
usfmtc-0.4.3.dist-info/WHEEL
usfmtc-0.4.3.dist-info/entry_points.txt
usfmtc-0.4.3.dist-info/top_level.txt
usfmtc-0.4.3.dist-info/RECORD
