Metadata-Version: 2.4
Name: usfmtc
Version: 0.4.3
Summary: USFM reference parser
Author-email: USFM Technical Committee <fonts@sil.org>
License: MIT
Project-URL: Home-Page, https://github.com/usfm-bible/usfmtc
Classifier: Environment :: Console
Classifier: Programming Language :: Python :: 3.8
Classifier: Intended Audience :: Developers
Classifier: Topic :: Text Processing :: Markup
Requires-Python: >=3.8
License-File: LICENSE
Requires-Dist: rply
Requires-Dist: regex
Provides-Extra: dev
Requires-Dist: rply; extra == "dev"
Requires-Dist: regex; extra == "dev"
Requires-Dist: lxml; extra == "dev"
Requires-Dist: xmlutils; extra == "dev"
Dynamic: license-file
